baijiayun/__init__.py
baijiayun/client/__init__.py
baijiayun/client/base.py
baijiayun/client/api/__init__.py
baijiayun/client/api/base.py
baijiayun/client/api/doc.py
baijiayun/client/api/evaluation.py
baijiayun/client/api/hudong.py
baijiayun/client/api/live.py
baijiayun/client/api/live_account.py
baijiayun/client/api/live_setting.py
baijiayun/client/api/notice.py
baijiayun/client/api/playback.py
baijiayun/client/api/quiz.py
baijiayun/client/api/room.py
baijiayun/client/api/room_data.py
baijiayun/client/api/small_course.py
baijiayun/client/api/sub_account.py
baijiayun/client/api/video.py
baijiayun/client/api/video_account.py
baijiayun/client/api/video_data.py
baijiayun/core/__init__.py
baijiayun/core/exceptions.py
baijiayun/core/utils.py
baijiayun/storage/__init__.py
baijiayun/storage/cache.py
baijiayun/storage/kvstorage.py
baijiayun/storage/memorystorage.py
baijiayun-1.0.1.dist-info/LICENSE
baijiayun-1.0.1.dist-info/METADATA
baijiayun-1.0.1.dist-info/WHEEL
baijiayun-1.0.1.dist-info/top_level.txt
baijiayun-1.0.1.dist-info/RECORD
